crispcore/__init__.py
crispcore/py.typed
crispcore-0.1.0.dist-info/WHEEL
crispcore-0.1.0.dist-info/METADATA
crispcore-0.1.0.dist-info/RECORD
